{"ResponseCode": "200", "ResponseMessage": "Success", "Response": {"ResultatsParArcher": [{"id": "818482", "nom": "LEVEILLE", "prenom": "CYNTHIA", "licence_code": "0818482E", "date_licence": "06/09/2025", "saison": "2026", "club": "CHATEAUBRIANT", "club_code": "1244035", "region": "COMITE REGIONAL DES PAYS DE LA LOIRE", "region_code": "CR12", "departement": "COMITE DEPARTEMENTAL LOIRE ATLANTIQUE", "departement_code": "44000", "championnats": {"officiels": {"S": {"discipline": "Tir à 18m", "discipline_code": "S", "championnat": "Individuel Tir à 18m 2026", "classements": [{"classement": "Scratch Femme Arc Nu 2026", "arme": "Arc Nu", "arme_code": "B", "sexe": "Femme", "sexe_code": "F", "categories_age": {"U21": "U21", "S1": "Senior 1", "S2": "Senior 2", "S3": "Senior 3"}, "categories": "Scratch (U21, Senior 1, Senior 2, Senior 3)", "moyenne": "485", "scores": {"1": "491", "2": "485", "3": "481"}, "distances": ["18m - 40cm", "25m - 60cm"]}, {"classement": "Adulte Femme Arc Nu 2026", "arme": "Arc Nu", "arme_code": "B", "sexe": "Femme", "sexe_code": "F", "categories_age": {"U21": "U21", "S1": "Senior 1", "S2": "Senior 2", "S3": "Senior 3"}, "categories": "U21, Senior 1, Senior 2, Senior 3", "moyenne": "485", "scores": {"1": "491", "2": "485", "3": "481"}, "distances": ["25m - 60cm", "18m - 40cm"], "epreuves": [{"date": "04/01/2026", "nom": "TARGET - CHATEAUBRIANT", "Categorie": "S1FBB", "CategorieSurclassement": "S1", "SCORE_TOTAL": "972", "PAILLE": "0", "DIX": "16", "NEUF": "40", "PLACE_QUALIF": "1", "SCORE_DIST1": "251", "SCORE_DIST2": "240", "SCORE_DIST3": "238", "SCORE_DIST4": "243", "SCORE_24": 0, "SCORE_16": 0, "SCORE_8": 0, "SCORE_QUART": 0, "SCORE_DEMI": 0, "SCORE_PETITE_FINAL": 0, "SCORE_FINAL": 0, "PLACE_DEF": "0", "NUM_DEPART": "1"}, {"date": "31/01/2026", "nom": "CD44 EQUIPE BB-CL ET CO À LA TURBALLE - LA TURBALLE", "Categorie": "S1FBB", "CategorieSurclassement": "S1", "SCORE_TOTAL": "485", "PAILLE": "0", "DIX": "8", "NEUF": "18", "PLACE_QUALIF": "2", "SCORE_DIST1": "234", "SCORE_DIST2": "251", "SCORE_DIST3": "0", "SCORE_DIST4": "0", "SCORE_24": 0, "SCORE_16": 0, "SCORE_8": 0, "SCORE_QUART": 0, "SCORE_DEMI": 0, "SCORE_PETITE_FINAL": 0, "SCORE_FINAL": 0, "PLACE_DEF": "0", "NUM_DEPART": "1"}, {"date": "29/11/2025", "nom": "CONCOURS SALLE ORVAULT - ORVAULT", "Categorie": "S1FBB", "CategorieSurclassement": "S1", "SCORE_TOTAL": "481", "PAILLE": "0", "DIX": "4", "NEUF": "0", "PLACE_QUALIF": "4", "SCORE_DIST1": "241", "SCORE_DIST2": "240", "SCORE_DIST3": "0", "SCORE_DIST4": "0", "SCORE_24": 0, "SCORE_16": 0, "SCORE_8": 0, "SCORE_QUART": 0, "SCORE_DEMI": 0, "SCORE_PETITE_FINAL": 0, "SCORE_FINAL": 0, "PLACE_DEF": "0", "NUM_DEPART": "1"}, {"date": "19/12/2025", "nom": "TIR A 18M &#x28;5 DEPARTS ABCD, 6 CIBLES&#x29; - ESPACE INTERGENERATION A LIFFRE", "Categorie": "S1FBB", "CategorieSurclassement": "S1", "SCORE_TOTAL": "481", "PAILLE": "0", "DIX": "13", "NEUF": "14", "PLACE_QUALIF": "1", "SCORE_DIST1": "239", "SCORE_DIST2": "242", "SCORE_DIST3": "0", "SCORE_DIST4": "0", "SCORE_24": 0, "SCORE_16": 0, "SCORE_8": 0, "SCORE_QUART": 0, "SCORE_DEMI": 0, "SCORE_PETITE_FINAL": 0, "SCORE_FINAL": 0, "PLACE_DEF": "0", "NUM_DEPART": "2"}, {"date": "19/12/2025", "nom": "TIR A 18M &#x28;5 DEPARTS ABCD, 6 CIBLES&#x29; - ESPACE INTERGENERATION A LIFFRE", "Categorie": "S1FBB", "CategorieSurclassement": "S1", "SCORE_TOTAL": "461", "PAILLE": "0", "DIX": "9", "NEUF": "14", "PLACE_QUALIF": "1", "SCORE_DIST1": "238", "SCORE_DIST2": "223", "SCORE_DIST3": "0", "SCORE_DIST4": "0", "SCORE_24": 0, "SCORE_16": 0, "SCORE_8": 0, "SCORE_QUART": 0, "SCORE_DEMI": 0, "SCORE_PETITE_FINAL": 0, "SCORE_FINAL": 0, "PLACE_DEF": "0", "NUM_DEPART": "1"}, {"date": "25/01/2026", "nom": "CHAMPIONNAT DÉPARTEMENTAL SALLE ADULTES  - GUÉRANDE ", "Categorie": "S1FBB", "CategorieSurclassement": "S1", "SCORE_TOTAL": "479", "PAILLE": "0", "DIX": "6", "NEUF": "18", "PLACE_QUALIF": "3", "SCORE_DIST1": "244", "SCORE_DIST2": "235", "SCORE_DIST3": "0", "SCORE_DIST4": "0", "SCORE_24": 0, "SCORE_16": 0, "SCORE_8": 0, "SCORE_QUART": 0, "SCORE_DEMI": 0, "SCORE_PETITE_FINAL": 0, "SCORE_FINAL": 0, "PLACE_DEF": "1", "NUM_DEPART": "1"}, {"date": "08/11/2025", "nom": "COMPÉTITION SALLE 2*18M - 4DÉPART - SAINT JACQUES DE LA LANDE", "Categorie": "S1FBB", "CategorieSurclassement": "S1", "SCORE_TOTAL": "452", "PAILLE": "0", "DIX": "5", "NEUF": "18", "PLACE_QUALIF": "2", "SCORE_DIST1": "242", "SCORE_DIST2": "210", "SCORE_DIST3": "0", "SCORE_DIST4": "0", "SCORE_24": 0, "SCORE_16": 0, "SCORE_8": 0, "SCORE_QUART": 0, "SCORE_DEMI": 0, "SCORE_PETITE_FINAL": 0, "SCORE_FINAL": 0, "PLACE_DEF": "0", "NUM_DEPART": "2"}, {"date": "08/11/2025", "nom": "COMPÉTITION SALLE 2*18M - 4DÉPART - SAINT JACQUES DE LA LANDE", "Categorie": "S1FBB", "CategorieSurclassement": "S1", "SCORE_TOTAL": "451", "PAILLE": "0", "DIX": "10", "NEUF": "7", "PLACE_QUALIF": "3", "SCORE_DIST1": "239", "SCORE_DIST2": "212", "SCORE_DIST3": "0", "SCORE_DIST4": "0", "SCORE_24": 0, "SCORE_16": 0, "SCORE_8": 0, "SCORE_QUART": 0, "SCORE_DEMI": 0, "SCORE_PETITE_FINAL": 0, "SCORE_FINAL": 0, "PLACE_DEF": "0", "NUM_DEPART": "1"}, {"date": "11/10/2025", "nom": "TIR SALLE CANDE 11 ET 12 OCTOBRE 2025 - CANDE", "Categorie": "S1FBB", "CategorieSurclassement": "S1", "SCORE_TOTAL": "435", "PAILLE": "0", "DIX": "4", "NEUF": "9", "PLACE_QUALIF": "2", "SCORE_DIST1": "212", "SCORE_DIST2": "223", "SCORE_DIST3": "0", "SCORE_DIST4": "0", "SCORE_24": 0, "SCORE_16": 0, "SCORE_8": 0, "SCORE_QUART": 0, "SCORE_DEMI": 0, "SCORE_PETITE_FINAL": 0, "SCORE_FINAL": 0, "PLACE_DEF": "0", "NUM_DEPART": "1"}, {"date": "01/11/2025", "nom": "CONCOURS SALLE DOMLOUP 4 DEPART 11CIBLES - DOMLOUP", "Categorie": "S1FBB", "CategorieSurclassement": "S1", "SCORE_TOTAL": "425", "PAILLE": "0", "DIX": "0", "NEUF": "0", "PLACE_QUALIF": "2", "SCORE_DIST1": "207", "SCORE_DIST2": "218", "SCORE_DIST3": "0", "SCORE_DIST4": "0", "SCORE_24": 0, "SCORE_16": 0, "SCORE_8": 0, "SCORE_QUART": 0, "SCORE_DEMI": 0, "SCORE_PETITE_FINAL": 0, "SCORE_FINAL": 0, "PLACE_DEF": "0", "NUM_DEPART": "1"}]}]}, "C": {"discipline": "Tir en Campagne", "discipline_code": "C", "championnat": "Individuel Tir en Campagne 2026", "classements": [{"classement": "Scratch Femme Bare Bow 2026", "arme": "Arc Nu", "arme_code": "B", "sexe": "Femme", "sexe_code": "F", "categories_age": {"U21": "U21", "S1": "Senior 1", "S2": "Senior 2", "S3": "Senior 3"}, "categories": "Scratch (U21, Senior 1, Senior 2, Senior 3)", "moyenne": "241", "scores": {"1": "249", "2": "234", "3": "0"}, "distances": ["Piquet 2"], "epreuves": [{"date": "22/03/2026", "nom": "TIR EN CAMPAGNE D&apos;ORVAULT - ORVAULT", "Categorie": "S1FBB", "CategorieSurclassement": "S1", "SCORE_TOTAL": "249", "PAILLE": "0", "DIX": "0", "NEUF": "0", "PLACE_QUALIF": "1", "SCORE_DIST1": "249", "SCORE_DIST2": "0", "SCORE_DIST3": "0", "SCORE_DIST4": "0", "SCORE_24": 0, "SCORE_16": 0, "SCORE_8": 0, "SCORE_QUART": 0, "SCORE_DEMI": 0, "SCORE_PETITE_FINAL": 0, "SCORE_FINAL": 0, "PLACE_DEF": "0", "NUM_DEPART": "1"}, {"date": "07/09/2025", "nom": "CAMPAGNE CANDÉ 07 SEPTEMBRE 2025 - SEGRE", "Categorie": "S1FBB", "CategorieSurclassement": "S1", "SCORE_TOTAL": "234", "PAILLE": "0", "DIX": "3", "NEUF": "7", "PLACE_QUALIF": "1", "SCORE_DIST1": "234", "SCORE_DIST2": "0", "SCORE_DIST3": "0", "SCORE_DIST4": "0", "SCORE_24": 0, "SCORE_16": 0, "SCORE_8": 0, "SCORE_QUART": 0, "SCORE_DEMI": 0, "SCORE_PETITE_FINAL": 0, "SCORE_FINAL": 0, "PLACE_DEF": "0", "NUM_DEPART": "1"}]}, {"classement": "Senior 1 Femme Bare Bow 2026", "arme": "Arc Nu", "arme_code": "B", "sexe": "Femme", "sexe_code": "F", "categories_age": {"S1": "Senior 1"}, "categories": "Senior 1", "moyenne": "241", "scores": {"1": "249", "2": "234", "3": "0"}, "distances": ["Piquet 2"]}, {"classement": "U21-Senior 1 Femme Bare Bow 2026", "arme": "Arc Nu", "arme_code": "B", "sexe": "Femme", "sexe_code": "F", "categories_age": {"U21": "U21", "S1": "Senior 1"}, "categories": "U21, Senior 1", "moyenne": "161", "scores": {"1": "249", "2": "234", "3": "0"}, "distances": ["Piquet 2"], "epreuves": [{"date": "22/03/2026", "nom": "TIR EN CAMPAGNE D&apos;ORVAULT - ORVAULT", "Categorie": "S1FBB", "CategorieSurclassement": "S1", "SCORE_TOTAL": "249", "PAILLE": "0", "DIX": "0", "NEUF": "0", "PLACE_QUALIF": "1", "SCORE_DIST1": "249", "SCORE_DIST2": "0", "SCORE_DIST3": "0", "SCORE_DIST4": "0", "SCORE_24": 0, "SCORE_16": 0, "SCORE_8": 0, "SCORE_QUART": 0, "SCORE_DEMI": 0, "SCORE_PETITE_FINAL": 0, "SCORE_FINAL": 0, "PLACE_DEF": "0", "NUM_DEPART": "1"}, {"date": "07/09/2025", "nom": "CAMPAGNE CANDÉ 07 SEPTEMBRE 2025 - SEGRE", "Categorie": "S1FBB", "CategorieSurclassement": "S1", "SCORE_TOTAL": "234", "PAILLE": "0", "DIX": "3", "NEUF": "7", "PLACE_QUALIF": "1", "SCORE_DIST1": "234", "SCORE_DIST2": "0", "SCORE_DIST3": "0", "SCORE_DIST4": "0", "SCORE_24": 0, "SCORE_16": 0, "SCORE_8": 0, "SCORE_QUART": 0, "SCORE_DEMI": 0, "SCORE_PETITE_FINAL": 0, "SCORE_FINAL": 0, "PLACE_DEF": "0", "NUM_DEPART": "1"}]}]}}, "non_officiels": []}}]}}