{"ResponseCode": "200", "ResponseMessage": "Success", "Response": {"PalmaresArray": [{"id": "1118546", "nom": "BELLEIL", "prenom": "PATRICK", "licence_code": "1055503Z", "date_licence": "11/09/2025", "saison": "2026", "club": "REZE", "club_code": "1244018", "region": "COMITE REGIONAL DES PAYS DE LA LOIRE", "region_code": "CR12", "departement": "COMITE DEPARTEMENTAL LOIRE ATLANTIQUE", "departement_code": "44000", "championnats": {"officiels": {"N": {"discipline": "Tir Nature", "discipline_code": "N", "championnat": "Individuel Tir Parcours Nature 2026", "classements": [{"classement": "Senior 2 Homme Bare Bow 2026", "arme": "Arc Nu", "arme_code": "C", "sexe": "Homme", "sexe_code": "H", "categories_age": {"S2": "Senior 2"}, "categories": "Senior 2", "place": "285", "score_total": "103", "scores": {"1": "310", "2": "0", "3": "0"}, "distances": ["Piquet 1"]}]}}, "non_officiels": []}}]}}